arr2img/__init__.py
arr2img-0.0.0.0.0.0.1.dist-info/LICENSE
arr2img-0.0.0.0.0.0.1.dist-info/METADATA
arr2img-0.0.0.0.0.0.1.dist-info/WHEEL
arr2img-0.0.0.0.0.0.1.dist-info/top_level.txt
arr2img-0.0.0.0.0.0.1.dist-info/RECORD
