Metadata-Version: 2.1
Name: arr2img
Version: 0.0.0.0.0.0.1
Summary: Convert any numpy array to image so that you can show it.
Author: azzhu
Author-email: zhu.qingjie@qq.com
License: MIT
Classifier: Programming Language :: Python :: 3
Classifier: License :: OSI Approved :: MIT License
Classifier: Operating System :: OS Independent
Requires-Python: >=3
License-File: LICENSE
Requires-Dist: numpy
